flamapy/metamodels/bdd_metamodel/__init__.py
flamapy/metamodels/bdd_metamodel/models/__init__.py
flamapy/metamodels/bdd_metamodel/models/bdd_model.py
flamapy/metamodels/bdd_metamodel/models/utils/__init__.py
flamapy/metamodels/bdd_metamodel/models/utils/txtcnf.py
flamapy/metamodels/bdd_metamodel/operations/__init__.py
flamapy/metamodels/bdd_metamodel/operations/bdd_commonality_factor.py
flamapy/metamodels/bdd_metamodel/operations/bdd_configurations.py
flamapy/metamodels/bdd_metamodel/operations/bdd_configurations_number.py
flamapy/metamodels/bdd_metamodel/operations/bdd_core_features.py
flamapy/metamodels/bdd_metamodel/operations/bdd_dead_features.py
flamapy/metamodels/bdd_metamodel/operations/bdd_feature_inclusion_probability.py
flamapy/metamodels/bdd_metamodel/operations/bdd_homogeneity.py
flamapy/metamodels/bdd_metamodel/operations/bdd_metrics.py
flamapy/metamodels/bdd_metamodel/operations/bdd_product_distribution.py
flamapy/metamodels/bdd_metamodel/operations/bdd_pure_optional_features.py
flamapy/metamodels/bdd_metamodel/operations/bdd_sampling.py
flamapy/metamodels/bdd_metamodel/operations/bdd_satisfiable.py
flamapy/metamodels/bdd_metamodel/operations/bdd_satisfiable_configuration.py
flamapy/metamodels/bdd_metamodel/operations/bdd_unique_features.py
flamapy/metamodels/bdd_metamodel/operations/bdd_variability.py
flamapy/metamodels/bdd_metamodel/operations/bdd_variant_features.py
flamapy/metamodels/bdd_metamodel/operations/interfaces/__init__.py
flamapy/metamodels/bdd_metamodel/operations/interfaces/commonality_factor.py
flamapy/metamodels/bdd_metamodel/operations/interfaces/feature_inclusion_probability.py
flamapy/metamodels/bdd_metamodel/operations/interfaces/homogeneity.py
flamapy/metamodels/bdd_metamodel/operations/interfaces/product_distribution.py
flamapy/metamodels/bdd_metamodel/operations/interfaces/pure_optional_features.py
flamapy/metamodels/bdd_metamodel/operations/interfaces/unique_features.py
flamapy_bdd-2.0.1.dist-info/METADATA
flamapy_bdd-2.0.1.dist-info/WHEEL
flamapy_bdd-2.0.1.dist-info/top_level.txt
flamapy_bdd-2.0.1.dist-info/RECORD
