Metadata-Version: 2.1
Name: flamapy-bdd
Version: 2.0.1
Summary: bdd-plugin for the automated analysis of feature models
Home-page: https://github.com/flamapy/bdd_metamodel
Author: Flamapy
Author-email: flamapy@us.es
License: UNKNOWN
Platform: UNKNOWN
Classifier: Programming Language :: Python :: 3
Classifier: License :: OSI Approved :: GNU General Public License v3 or later (GPLv3+)
Classifier: Operating System :: OS Independent
Requires-Python: >=3.9
Provides-Extra: dev
